eaiesbcalculator/__init__.py
eaiesbcalculator-0.4.dist-info/LICENCE.txt
eaiesbcalculator-0.4.dist-info/METADATA
eaiesbcalculator-0.4.dist-info/WHEEL
eaiesbcalculator-0.4.dist-info/top_level.txt
eaiesbcalculator-0.4.dist-info/RECORD
