Metadata-Version: 2.1
Name: eaiesbcalculator
Version: 0.4
Summary: Calculator demo first package
Home-page: UNKNOWN
Author: vineel
Author-email: vineelmarreddy2001@gmail.com
License: UNKNOWN
Platform: UNKNOWN
Classifier: Programming Language :: Python :: 3
Classifier: License :: OSI Approved :: MIT License
Classifier: Operating System :: OS Independent
